<Model id="58">
	<Authors>
		<Author id="1">
			<Name>First name, last name</Name>
			<Link/>
		</Author>
	</Authors>
	<Model_name>2002 Total Phosphorus SPARROW Model for the Missouri River Basin</Model_name>
	<MRB>MRB04</MRB>
	<Constituent>
		<Name>Phosphorus</Name>
		<Units>kg/yr</Units>
		<Description>1992 regional E2RF1 total phosphorus model, includes U.S. portion of Oldman River Basin and the Missouri River Basin</Description>
	</Constituent>
	<Sources>
		<Source id="All">
			<Name>All</Name>
			<Units/>
			<Description>All sources combined.</Description>
		</Source>
		<Source id="1">
			<Name>Manure P</Name>
			<Units>kg</Units>
			<Description>Phosphorus from Manure</Description>
		</Source>
		<Source id="2">
			<Name>Farm Fertilizer P</Name>
			<Units>kg</Units>
			<Description>Phosphorus from Farm Fertilizer</Description>
		</Source>
		<Source id="3">
			<Name>Developed Land</Name>
			<Units>sq km</Units>
			<Description>2001 NLCD developed land area</Description>
		</Source>
		<Source id="4">
			<Name>Channel Length</Name>
			<Units>m</Units>
			<Description>Reach length of channels (Q>1.13 cms)</Description>
		</Source>
		<Source id="5">
			<Name>Point Sources</Name>
			<Units>kg</Units>
			<Description>Phosphorus from point sources</Description>
		</Source>
	</Sources>
	<Model_papers>
		<Paper id="1">
			<Link link=""/>
			<Citation_mods>
				<identifier type=""/>
				<identifier type=""/>
				<identifier type=""/>
				<genre/>
				<titleInfo>
					<title/>
				</titleInfo>
				<originInfo>
					<dateOther/>
					<publisher/>
					<placeTerm/>
				</originInfo>
				<name>
					<namePart/>
					<role>Author</role>
				</name>
				<physicalDescription>
					<form/>
					<form/>
					<form/>
				</physicalDescription>
				<note type="citation/reference"/>
				<edition/>
				<languageTerm/>
			</Citation_mods>
		</Paper>
	</Model_papers>
	<CommonTerms>
		<Term id="For Source">
			Each model has different sources that the modeler has determined to be statistically significant.
			Choose a source from the list to present data only from that source.  This model contains these sources:
			
			<dl>
				<!-- These names could be improved, do we have updated info from Greg? -->
				<dt>All</dt>
				<dd>Not really a separate source, it just tallies all the sources together.  Reported in kg.</dd>
				<dt>Manure P</dt>
				<dd>Sum total of Phosphorus from Manure in Confined and Unconfined Operations (kg)</dd>
				<dt>Farm Fertilizer P</dt>
				<dd>Sum total of Phosphorous Fertilizer from Farms (kg)</dd>
				<dt>Developed Land</dt>
				<dd>2001 National Land Cover Dataset developed land area, includes developed open space, low, medium, and high intensity (sqkm)</dd>
				<dt>Channel Length</dt>
				<dd>Reach length of channels in streams with discharge greater than 1.13 cms (m)</dd>				
				<dt>Point Sources</dt>
				<dd>Sum total of phosphorus from point sources (average of 1992, 1997, and 2002 data) (kg)</dd>

			</dl>
		</Term>
	</CommonTerms>
		
</Model>
